{
  "warrior":
  {
    "name": "Warrior",
    "archetype": ["Fighter"],
    "life_point_multiple_cost": 15,
    "life_points_per_level": 15,
    "initiative_per_level": 5,
    "martial_knowledge_per_level": 25,
    "innate_psychic_points_per_level": 0.34,
    "combat_ability_limit": 0.6,
    "supernatural_ability_limit": 0.5,
    "psychic_ability_limit": 0.5,
    "attack_cost": 2,
    "block_cost": 2,
    "dodge_cost": 2,
    "wear_armor_cost": 2,
    "ki_cost": 2,
    "accumulation_multiple_cost": 20,
    "5_zeon_cost": 3,
    "ma_multiple_cost": 70,
    "magic_projection_cost": 3,
    "summon_cost": 3,
    "control_cost": 3,
    "bind_cost": 3,
    "banish_cost": 3,
    "psychic_points_cost": 20,
    "psychic_projection_cost": 3,
    "athletics_cost": 2,
    "social_cost": 2,
    "perceptive_cost": 2,
    "intellectual_cost": 3,
    "vigor_cost": 2,
    "subterfuge_cost": 2,
    "creative_cost": 2,
    "reduced_costs":
    {
      "feats_of_strength": 1
    },
    "innate_bonuses":
    {
      "attack_per_level": 5,
      "block_per_level": 5,
      "wear_armor_per_level": 5,
      "feats_of_strength_per_level": 5
    },
    "special": {}
  },

  "acrobatic_warrior":
  {
    "name": "Acrobatic Warrior",
    "archetype": ["Fighter"],
    "life_point_multiple_cost": 20,
    "life_points_per_level": 10,
    "initiative_per_level": 10,
    "martial_knowledge_per_level": 25,
    "innate_psychic_points_per_level": 0.34,
    "combat_ability_limit": 0.6,
    "supernatural_ability_limit": 0.5,
    "psychic_ability_limit": 0.5,
    "attack_cost": 2,
    "block_cost": 2,
    "dodge_cost": 2,
    "wear_armor_cost": 2,
    "ki_cost": 2,
    "accumulation_multiple_cost": 20,
    "5_zeon_cost": 3,
    "ma_multiple_cost": 70,
    "magic_projection_cost": 3,
    "summon_cost": 3,
    "control_cost": 3,
    "bind_cost": 3,
    "banish_cost": 3,
    "psychic_points_cost": 20,
    "psychic_projection_cost": 3,
    "athletics_cost": 2,
    "social_cost": 2,
    "perceptive_cost": 2,
    "intellectual_cost": 3,
    "vigor_cost": 2,
    "subterfuge_cost": 2,
    "creative_cost": 2,
    "reduced_costs": {},
    "innate_bonuses":
    {
      "attack_per_level": 5,
      "dodge_per_level": 5,
      "acrobatics_per_level": 10,
      "jump_per_level": 10,
      "athleticism_per_level": 10,
      "sleight_of_hand_per_level": 10,
      "style_per_level": 10
    },
    "special": {}
  },

  "paladin":
  {
    "name": "Paladin",
    "archetype": ["Fighter"],
    "life_point_multiple_cost": 15,
    "life_points_per_level": 15,
    "initiative_per_level": 5,
    "martial_knowledge_per_level": 20,
    "innate_psychic_points_per_level": 0.34,
    "combat_ability_limit": 0.6,
    "supernatural_ability_limit": 0.5,
    "psychic_ability_limit": 0.5,
    "attack_cost": 2,
    "block_cost": 2,
    "dodge_cost": 2,
    "wear_armor_cost": 2,
    "ki_cost": 2,
    "accumulation_multiple_cost": 20,
    "5_zeon_cost": 2,
    "ma_multiple_cost": 60,
    "magic_projection_cost": 3,
    "summon_cost": 3,
    "control_cost": 3,
    "bind_cost": 3,
    "banish_cost": 1,
    "psychic_points_cost": 20,
    "psychic_projection_cost": 3,
    "athletics_cost": 2,
    "social_cost": 1,
    "perceptive_cost": 2,
    "intellectual_cost": 2,
    "vigor_cost": 2,
    "subterfuge_cost": 3,
    "creative_cost": 2,
    "reduced_costs":
    {
      "withstand_pain": 1
    },
    "innate_bonuses":
    {
      "block_per_level": 5,
      "wear_armor_per_level": 10,
      "banish_per_level": 10,
      "zeon_per_level": 20,
      "leadership_per_level": 10,
      "withstand_pain_per_level": 10,
      "style_per_level": 5
    },
    "special":
    {
      "exchange":
      {
        "banish_per_level": 10,
        "zeon_per_level": 20,
        "for":
        {
          "composure_per_level": 10
        }
      }
    }
  },

  "dark_paladin":
  {
    "name": "Dark Paladin",
    "archetype": ["Fighter"],
    "life_point_multiple_cost": 15,
    "life_points_per_level": 15,
    "initiative_per_level": 5,
    "martial_knowledge_per_level": 20,
    "innate_psychic_points_per_level": 0.34,
    "combat_ability_limit": 0.6,
    "supernatural_ability_limit": 0.5,
    "psychic_ability_limit": 0.5,
    "attack_cost": 2,
    "block_cost": 2,
    "dodge_cost": 2,
    "wear_armor_cost": 2,
    "ki_cost": 2,
    "accumulation_multiple_cost": 20,
    "5_zeon_cost": 2,
    "ma_multiple_cost": 60,
    "magic_projection_cost": 3,
    "summon_cost": 3,
    "control_cost": 1,
    "bind_cost": 3,
    "banish_cost": 3,
    "psychic_points_cost": 20,
    "psychic_projection_cost": 3,
    "athletics_cost": 2,
    "social_cost": 1,
    "perceptive_cost": 2,
    "intellectual_cost": 2,
    "vigor_cost": 2,
    "subterfuge_cost": 2,
    "creative_cost": 2,
    "reduced_costs":
    {
      "composure": 1
    },
    "innate_bonuses":
    {
      "attack_per_level": 5,
      "wear_armor_per_level": 5,
      "control_per_level": 10,
      "zeon_per_level": 20
    },
    "special":
    {
      "exchange":
      {
        "control_per_level": 10,
        "zeon_per_level": 20,
        "for":
        {
          "withstand_pain_per_level": 10
        }
      }
    }
  },

  "weaponmaster":
  {
    "name": "Weaponmaster",
    "archetype": ["Fighter"],
    "life_point_multiple_cost": 10,
    "life_points_per_level": 20,
    "initiative_per_level": 5,
    "martial_knowledge_per_level": 10,
    "innate_psychic_points_per_level": 0.34,
    "combat_ability_limit": 0.6,
    "supernatural_ability_limit": 0.5,
    "psychic_ability_limit": 0.5,
    "attack_cost": 2,
    "block_cost": 2,
    "dodge_cost": 2,
    "wear_armor_cost": 1,
    "ki_cost": 3,
    "accumulation_multiple_cost": 30,
    "5_zeon_cost": 3,
    "ma_multiple_cost": 70,
    "magic_projection_cost": 3,
    "summon_cost": 3,
    "control_cost": 3,
    "bind_cost": 3,
    "banish_cost": 3,
    "psychic_points_cost": 20,
    "psychic_projection_cost": 3,
    "athletics_cost": 2,
    "social_cost": 2,
    "perceptive_cost": 2,
    "intellectual_cost": 3,
    "vigor_cost": 1,
    "subterfuge_cost": 3,
    "creative_cost": 2,
    "reduced_costs":
    {
      "modules": 0.5
    },
    "innate_bonuses":
    {
      "attack_per_level": 5,
      "block_per_level": 5,
      "wear_armor_per_level": 10
    },
    "special": {}
  },

  "technician":
  {
    "name": "Technician",
    "archetype": ["Domine"],
    "life_point_multiple_cost": 20,
    "life_points_per_level": 5,
    "initiative_per_level": 5,
    "martial_knowledge_per_level": 50,
    "innate_psychic_points_per_level": 0.34,
    "combat_ability_limit": 0.6,
    "supernatural_ability_limit": 0.5,
    "psychic_ability_limit": 0.5,
    "attack_cost": 2,
    "block_cost": 2,
    "dodge_cost": 2,
    "wear_armor_cost": 2,
    "ki_cost": 1,
    "accumulation_multiple_cost": 10,
    "5_zeon_cost": 3,
    "ma_multiple_cost": 70,
    "magic_projection_cost": 3,
    "summon_cost": 3,
    "control_cost": 3,
    "bind_cost": 3,
    "banish_cost": 3,
    "psychic_points_cost": 20,
    "psychic_projection_cost": 3,
    "athletics_cost": 2,
    "social_cost": 2,
    "perceptive_cost": 2,
    "intellectual_cost": 3,
    "vigor_cost": 2,
    "subterfuge_cost": 2,
    "creative_cost": 2,
    "reduced_costs": {},
    "innate_bonuses":
    {
      "attack_per_level": 5
    },
    "special": {}
  },

  "tao":
  {
    "name": "Tao",
    "archetype": ["Fighter", "Domine"],
    "life_point_multiple_cost": 20,
    "life_points_per_level": 10,
    "initiative_per_level": 5,
    "martial_knowledge_per_level": 30,
    "innate_psychic_points_per_level": 0.34,
    "combat_ability_limit": 0.6,
    "supernatural_ability_limit": 0.5,
    "psychic_ability_limit": 0.5,
    "attack_cost": 2,
    "block_cost": 2,
    "dodge_cost": 2,
    "wear_armor_cost": 2,
    "ki_cost": 2,
    "accumulation_multiple_cost": 15,
    "5_zeon_cost": 3,
    "ma_multiple_cost": 70,
    "magic_projection_cost": 3,
    "summon_cost": 3,
    "control_cost": 3,
    "bind_cost": 3,
    "banish_cost": 3,
    "psychic_points_cost": 20,
    "psychic_projection_cost": 3,
    "athletics_cost": 2,
    "social_cost": 2,
    "perceptive_cost": 2,
    "intellectual_cost": 3,
    "vigor_cost": 2,
    "subterfuge_cost": 2,
    "creative_cost": 2,
    "reduced_costs":
    {
      "martial_arts": 0.5
    },
    "innate_bonuses":
    {
      "style_per_level": 5
    },
    "special": {}
  },

  "ranger":
  {
    "name": "Ranger",
    "archetype": ["Fighter", "Prowler"],
    "life_point_multiple_cost": 20,
    "life_points_per_level": 10,
    "initiative_per_level": 5,
    "martial_knowledge_per_level": 20,
    "innate_psychic_points_per_level": 0.34,
    "combat_ability_limit": 0.6,
    "supernatural_ability_limit": 0.5,
    "psychic_ability_limit": 0.5,
    "attack_cost": 2,
    "block_cost": 2,
    "dodge_cost": 2,
    "wear_armor_cost": 2,
    "ki_cost": 2,
    "accumulation_multiple_cost": 25,
    "5_zeon_cost": 3,
    "ma_multiple_cost": 70,
    "magic_projection_cost": 3,
    "summon_cost": 3,
    "control_cost": 3,
    "bind_cost": 3,
    "banish_cost": 3,
    "psychic_points_cost": 20,
    "psychic_projection_cost": 3,
    "athletics_cost": 2,
    "social_cost": 2,
    "perceptive_cost": 1,
    "intellectual_cost": 3,
    "vigor_cost": 3,
    "subterfuge_cost": 2,
    "creative_cost": 2,
    "reduced_costs":
    {
      "trap_lore": 1,
      "herbal_lore": 2,
      "animals": 1,
      "medicine": 2
    },
    "innate_bonuses":
    {
      "attack_per_level": 5,
      "notice_per_level": 5,
      "search_per_level": 5,
      "track_per_level": 5,
      "trap_lore_per_level": 5,
      "animals_per_level": 5,
      "herbal_lore_per_level": 5,
      "detect_ki_per_level": 10
    },
    "special": {}
  },

  "shadow":
  {
    "name": "Shadow",
    "archetype": ["Fighter"],
    "life_point_multiple_cost": 20,
    "life_points_per_level": 5,
    "initiative_per_level": 10,
    "martial_knowledge_per_level": 25,
    "innate_psychic_points_per_level": 0.34,
    "combat_ability_limit": 0.6,
    "supernatural_ability_limit": 0.5,
    "psychic_ability_limit": 0.5,
    "attack_cost": 2,
    "block_cost": 3,
    "dodge_cost": 2,
    "wear_armor_cost": 2,
    "ki_cost": 2,
    "accumulation_multiple_cost": 20,
    "5_zeon_cost": 3,
    "ma_multiple_cost": 70,
    "magic_projection_cost": 3,
    "summon_cost": 3,
    "control_cost": 3,
    "bind_cost": 3,
    "banish_cost": 3,
    "psychic_points_cost": 20,
    "psychic_projection_cost": 3,
    "athletics_cost": 2,
    "social_cost": 2,
    "perceptive_cost": 2,
    "intellectual_cost": 3,
    "vigor_cost": 2,
    "subterfuge_cost": 2,
    "creative_cost": 2,
    "reduced_costs": {},
    "innate_bonuses":
    {
      "attack_per_level": 5,
      "dodge_per_level": 5,
      "notice_per_level": 10,
      "search_per_level": 10,
      "hide_per_level": 10,
      "stealth_per_level": 10,
      "ki_concealment_per_level": 5
    },
    "special": {}
  },

  "thief":
  {
    "name": "Thief",
    "archetype": ["Prowler"],
    "life_point_multiple_cost": 20,
    "life_points_per_level": 5,
    "initiative_per_level": 10,
    "martial_knowledge_per_level": 20,
    "innate_psychic_points_per_level": 0.34,
    "combat_ability_limit": 0.5,
    "supernatural_ability_limit": 0.5,
    "psychic_ability_limit": 0.5,
    "attack_cost": 2,
    "block_cost": 3,
    "dodge_cost": 2,
    "wear_armor_cost": 3,
    "ki_cost": 2,
    "accumulation_multiple_cost": 25,
    "5_zeon_cost": 3,
    "ma_multiple_cost": 70,
    "magic_projection_cost": 3,
    "summon_cost": 3,
    "control_cost": 3,
    "bind_cost": 3,
    "banish_cost": 3,
    "psychic_points_cost": 20,
    "psychic_projection_cost": 3,
    "athletics_cost": 1,
    "social_cost": 2,
    "perceptive_cost": 2,
    "intellectual_cost": 3,
    "vigor_cost": 3,
    "subterfuge_cost": 1,
    "creative_cost": 2,
    "reduced_costs":
    {
      "appraisal": 1
    },
    "innate_bonuses":
    {
      "dodge_per_level": 5,
      "notice_per_level": 5,
      "search_per_level": 5,
      "hide_per_level": 5,
      "stealth_per_level": 5,
      "trap_lore_per_level": 5,
      "sleight_of_hand_per_level": 5,
      "theft_per_level": 10,
      "ki_concealment_per_level": 5
    },
    "special": {}
  },

  "assassin":
  {
    "name": "Assassin",
    "archetype": ["Prowler"],
    "life_point_multiple_cost": 20,
    "life_points_per_level": 5,
    "initiative_per_level": 10,
    "martial_knowledge_per_level": 20,
    "innate_psychic_points_per_level": 0.34,
    "combat_ability_limit": 0.5,
    "supernatural_ability_limit": 0.5,
    "psychic_ability_limit": 0.5,
    "attack_cost": 2,
    "block_cost": 3,
    "dodge_cost": 2,
    "wear_armor_cost": 3,
    "ki_cost": 2,
    "accumulation_multiple_cost": 25,
    "5_zeon_cost": 3,
    "ma_multiple_cost": 70,
    "magic_projection_cost": 3,
    "summon_cost": 3,
    "control_cost": 3,
    "bind_cost": 3,
    "banish_cost": 3,
    "psychic_points_cost": 20,
    "psychic_projection_cost": 3,
    "athletics_cost": 2,
    "social_cost": 2,
    "perceptive_cost": 1,
    "intellectual_cost": 3,
    "vigor_cost": 3,
    "subterfuge_cost": 2,
    "creative_cost": 2,
    "reduced_costs":
    {
      "stealth": 1,
      "composure": 2,
      "memorize": 2
    },
    "innate_bonuses":
    {
      "attack_per_level": 5,
      "notice_per_level": 10,
      "search_per_level": 10,
      "hide_per_level": 10,
      "stealth_per_level": 10,
      "poisons_per_level": 10,
      "composure_per_level": 10,
      "trap_lore_per_level": 10
    },
    "special": {}
  },

  "wizard":
  {
    "name": "Wizard",
    "archetype": ["Mystic"],
    "life_point_multiple_cost": 20,
    "life_points_per_level": 5,
    "initiative_per_level": 5,
    "martial_knowledge_per_level": 10,
    "innate_psychic_points_per_level": 0.34,
    "combat_ability_limit": 0.5,
    "supernatural_ability_limit": 0.6,
    "psychic_ability_limit": 0.5,
    "attack_cost": 3,
    "block_cost": 3,
    "dodge_cost": 2,
    "wear_armor_cost": 3,
    "ki_cost": 3,
    "accumulation_multiple_cost": 30,
    "5_zeon_cost": 1,
    "ma_multiple_cost": 50,
    "magic_projection_cost": 2,
    "summon_cost": 2,
    "control_cost": 2,
    "bind_cost": 2,
    "banish_cost": 2,
    "psychic_points_cost": 20,
    "psychic_projection_cost": 3,
    "athletics_cost": 2,
    "social_cost": 2,
    "perceptive_cost": 2,
    "intellectual_cost": 2,
    "vigor_cost": 3,
    "subterfuge_cost": 2,
    "creative_cost": 2,
    "reduced_costs":
    {
      "magic_appraisal": 1
    },
    "innate_bonuses":
    {
      "zeon_per_level": 100,
      "magic_appraisal_per_level": 10,
      "occult_per_level": 5
    },
    "special": {}
  },

  "warlock":
  {
    "name": "Warlock",
    "archetype": ["Fighter", "Mystic"],
    "life_point_multiple_cost": 20,
    "life_points_per_level": 10,
    "initiative_per_level": 5,
    "martial_knowledge_per_level": 20,
    "innate_psychic_points_per_level": 0.34,
    "combat_ability_limit": 0.5,
    "supernatural_ability_limit": 0.5,
    "psychic_ability_limit": 0.5,
    "attack_cost": 2,
    "block_cost": 2,
    "dodge_cost": 2,
    "wear_armor_cost": 2,
    "ki_cost": 2,
    "accumulation_multiple_cost": 20,
    "5_zeon_cost": 1,
    "ma_multiple_cost": 50,
    "magic_projection_cost": 2,
    "summon_cost": 2,
    "control_cost": 2,
    "bind_cost": 2,
    "banish_cost": 2,
    "psychic_points_cost": 20,
    "psychic_projection_cost": 3,
    "athletics_cost": 2,
    "social_cost": 2,
    "perceptive_cost": 2,
    "intellectual_cost": 2,
    "vigor_cost": 2,
    "subterfuge_cost": 2,
    "creative_cost": 2,
    "reduced_costs": {},
    "innate_bonuses":
    {
      "attack_per_level": 5,
      "block_per_level": 5,
      "dodge_per_level": 5,
      "zeon_per_level": 20,
      "magic_appraisal_per_level": 5
    },
    "special": {}
  },

  "illusionist":
  {
    "name": "Illusionist",
    "archetype": ["Mystic", "Prowler"],
    "life_point_multiple_cost": 20,
    "life_points_per_level": 5,
    "initiative_per_level": 5,
    "martial_knowledge_per_level": 20,
    "innate_psychic_points_per_level": 0.34,
    "combat_ability_limit": 0.5,
    "supernatural_ability_limit": 0.6,
    "psychic_ability_limit": 0.5,
    "attack_cost": 3,
    "block_cost": 3,
    "dodge_cost": 2,
    "wear_armor_cost": 3,
    "ki_cost": 2,
    "accumulation_multiple_cost": 25,
    "5_zeon_cost": 1,
    "ma_multiple_cost": 60,
    "magic_projection_cost": 2,
    "summon_cost": 3,
    "control_cost": 3,
    "bind_cost": 3,
    "banish_cost": 3,
    "psychic_points_cost": 20,
    "psychic_projection_cost": 3,
    "athletics_cost": 2,
    "social_cost": 2,
    "perceptive_cost": 2,
    "intellectual_cost": 2,
    "vigor_cost": 3,
    "subterfuge_cost": 2,
    "creative_cost": 2,
    "reduced_costs":
    {
      "sleight_of_hand": 1,
      "persuasion": 1
    },
    "innate_bonuses":
    {
      "zeon_per_level": 75,
      "magic_appraisal_per_level": 5,
      "stealth_per_level": 10,
      "hide_per_level": 10,
      "sleight_of_hand_per_level": 10,
      "disguise_per_level": 5,
      "theft_per_level": 5,
      "persuasion_per_level": 5
    },
    "special": {}
  },

  "wizard mentalist":
  {
    "name": "Wizard Mentalist",
    "archetype": ["Mystic", "Psychic"],
    "life_point_multiple_cost": 20,
    "life_points_per_level": 5,
    "initiative_per_level": 5,
    "martial_knowledge_per_level": 10,
    "innate_psychic_points_per_level": 1,
    "combat_ability_limit": 0.5,
    "supernatural_ability_limit": 0.5,
    "psychic_ability_limit": 0.5,
    "attack_cost": 3,
    "block_cost": 3,
    "dodge_cost": 2,
    "wear_armor_cost": 3,
    "ki_cost": 3,
    "accumulation_multiple_cost": 30,
    "5_zeon_cost": 1,
    "ma_multiple_cost": 50,
    "magic_projection_cost": 2,
    "summon_cost": 2,
    "control_cost": 2,
    "bind_cost": 2,
    "banish_cost": 2,
    "psychic_points_cost": 10,
    "psychic_projection_cost": 2,
    "athletics_cost": 2,
    "social_cost": 2,
    "perceptive_cost": 2,
    "intellectual_cost": 2,
    "vigor_cost": 3,
    "subterfuge_cost": 2,
    "creative_cost": 2,
    "reduced_costs": {},
    "innate_bonuses":
    {
      "zeon_per_level": 100,
      "magic_appraisal_per_level": 10,
      "occult_per_level": 5
    },
    "special": {}
  },

  "summoner":
  {
    "name": "Summoner",
    "archetype": ["Mystic"],
    "life_point_multiple_cost": 20,
    "life_points_per_level": 5,
    "initiative_per_level": 5,
    "martial_knowledge_per_level": 10,
    "innate_psychic_points_per_level": 0.34,
    "combat_ability_limit": 0.5,
    "supernatural_ability_limit": 0.6,
    "psychic_ability_limit": 0.5,
    "attack_cost": 3,
    "block_cost": 3,
    "dodge_cost": 2,
    "wear_armor_cost": 3,
    "ki_cost": 3,
    "accumulation_multiple_cost": 30,
    "5_zeon_cost": 1,
    "ma_multiple_cost": 60,
    "magic_projection_cost": 3,
    "summon_cost": 1,
    "control_cost": 1,
    "bind_cost": 1,
    "banish_cost": 1,
    "psychic_points_cost": 20,
    "psychic_projection_cost": 3,
    "athletics_cost": 2,
    "social_cost": 2,
    "perceptive_cost": 2,
    "intellectual_cost": 3,
    "vigor_cost": 3,
    "subterfuge_cost": 2,
    "creative_cost": 2,
    "reduced_costs":
    {
      "occult": 1
    },
    "innate_bonuses":
    {
      "zeon_per_level": 50,
      "summon_per_level": 10,
      "control_per_level": 10,
      "bind_per_level": 10,
      "banish_per_level": 10,
      "magic_appraisal_per_level": 5,
      "occult_per_level": 10
    },
    "special": {}
  },

  "warrior summoner":
  {
    "name": "Warrior Summoner",
    "archetype": ["Fighter", "Mystic"],
    "life_point_multiple_cost": 20,
    "life_points_per_level": 10,
    "initiative_per_level": 5,
    "martial_knowledge_per_level": 20,
    "innate_psychic_points_per_level": 0.34,
    "combat_ability_limit": 0.5,
    "supernatural_ability_limit": 0.5,
    "psychic_ability_limit": 0.5,
    "attack_cost": 2,
    "block_cost": 2,
    "dodge_cost": 2,
    "wear_armor_cost": 2,
    "ki_cost": 2,
    "accumulation_multiple_cost": 20,
    "5_zeon_cost": 1,
    "ma_multiple_cost": 60,
    "magic_projection_cost": 3,
    "summon_cost": 1,
    "control_cost": 1,
    "bind_cost": 1,
    "banish_cost": 1,
    "psychic_points_cost": 20,
    "psychic_projection_cost": 3,
    "athletics_cost": 2,
    "social_cost": 2,
    "perceptive_cost": 2,
    "intellectual_cost": 2,
    "vigor_cost": 2,
    "subterfuge_cost": 2,
    "creative_cost": 2,
    "reduced_costs": {},
    "innate_bonuses":
    {
      "attack_per_level": 5,
      "block_per_level": 5,
      "dodge_per_level": 5,
      "wear_armor_per_level": 5,
      "zeon_per_level": 20,
      "summon_per_level": 5,
      "control_per_level": 5,
      "bind_per_level": 5,
      "banish_per_level": 5,
      "occult_per_level": 5
    },
    "special": {}
  },

  "mentalist":
  {
    "name": "Mentalist",
    "archetype": ["Psychic"],
    "life_point_multiple_cost": 20,
    "life_points_per_level": 5,
    "initiative_per_level": 5,
    "martial_knowledge_per_level": 10,
    "innate_psychic_points_per_level": 1,
    "combat_ability_limit": 0.5,
    "supernatural_ability_limit": 0.5,
    "psychic_ability_limit": 0.6,
    "attack_cost": 3,
    "block_cost": 3,
    "dodge_cost": 2,
    "wear_armor_cost": 3,
    "ki_cost": 3,
    "accumulation_multiple_cost": 30,
    "5_zeon_cost": 3,
    "ma_multiple_cost": 70,
    "magic_projection_cost": 3,
    "summon_cost": 3,
    "control_cost": 3,
    "bind_cost": 3,
    "banish_cost": 3,
    "psychic_points_cost": 10,
    "psychic_projection_cost": 2,
    "athletics_cost": 2,
    "social_cost": 2,
    "perceptive_cost": 2,
    "intellectual_cost": 3,
    "vigor_cost": 3,
    "subterfuge_cost": 2,
    "creative_cost": 2,
    "reduced_costs": {},
    "innate_bonuses": {},
    "special": {}
  },

  "warrior mentalist":
  {
    "name": "Warrior Mentalist",
    "archetype": ["Fighter", "Psychic"],
    "life_point_multiple_cost": 20,
    "life_points_per_level": 10,
    "initiative_per_level": 5,
    "martial_knowledge_per_level": 20,
    "innate_psychic_points_per_level": 1,
    "combat_ability_limit": 0.5,
    "supernatural_ability_limit": 0.5,
    "psychic_ability_limit": 0.5,
    "attack_cost": 2,
    "block_cost": 2,
    "dodge_cost": 2,
    "wear_armor_cost": 2,
    "ki_cost": 2,
    "accumulation_multiple_cost": 25,
    "5_zeon_cost": 3,
    "ma_multiple_cost": 70,
    "magic_projection_cost": 3,
    "summon_cost": 3,
    "control_cost": 3,
    "bind_cost": 3,
    "banish_cost": 3,
    "psychic_points_cost": 15,
    "psychic_projection_cost": 2,
    "athletics_cost": 2,
    "social_cost": 2,
    "perceptive_cost": 2,
    "intellectual_cost": 3,
    "vigor_cost": 2,
    "subterfuge_cost": 2,
    "creative_cost": 2,
    "reduced_costs": {},
    "innate_bonuses":
    {
      "attack_per_level": 5,
      "block_per_level": 5,
      "dodge_per_level": 5
    },
    "special": {}
  },

  "freelancer":
  {
    "name": "Freelancer",
    "archetype": ["Novel"],
    "life_point_multiple_cost": 20,
    "life_points_per_level": 5,
    "initiative_per_level": 5,
    "martial_knowledge_per_level": 20,
    "innate_psychic_points_per_level": 0.5,
    "combat_ability_limit": 0.6,
    "supernatural_ability_limit": 0.6,
    "psychic_ability_limit": 0.6,
    "attack_cost": 2,
    "block_cost": 2,
    "dodge_cost": 2,
    "wear_armor_cost": 2,
    "ki_cost": 2,
    "accumulation_multiple_cost": 20,
    "5_zeon_cost": 2,
    "ma_multiple_cost": 60,
    "magic_projection_cost": 2,
    "summon_cost": 2,
    "control_cost": 2,
    "bind_cost": 2,
    "banish_cost": 2,
    "psychic_points_cost": 20,
    "psychic_projection_cost": 2,
    "athletics_cost": 2,
    "social_cost": 2,
    "perceptive_cost": 2,
    "intellectual_cost": 2,
    "vigor_cost": 2,
    "subterfuge_cost": 2,
    "creative_cost": 2,
    "reduced_costs":
    {
      "change_class": 20
    },
    "innate_bonuses":
    {
      "zeon_per_level": 10,
      "free_bonuses": [5, 10]
    },
    "special": {}
  }
}
